{
  "gitSyncId": "670cad581d2c4329a60fbdeb_ae95c969-c0fd-4d17-842a-92ccb4a4a56d",
  "id": "Page1_deleteElement.deleteElementList",
  "pluginId": "js-plugin",
  "pluginType": "JS",
  "unpublishedAction": {
    "actionConfiguration": {
      "encodeParamsToggle": true,
      "jsArguments": [],
      "paginationType": "NONE",
      "timeoutInMillisecond": 10000
    },
    "collectionId": "Page1_deleteElement",
    "confirmBeforeExecute": false,
    "datasource": {
      "isAutoGenerated": false,
      "name": "UNUSED_DATASOURCE",
      "pluginId": "js-plugin"
    },
    "dynamicBindingPathList": [
      {
        "key": "body"
      }
    ],
    "executeOnLoad": false,
    "fullyQualifiedName": "deleteElement.deleteElementList",
    "name": "deleteElementList",
    "pageId": "Page1",
    "userSetOnLoad": false
  }
}